odoo/addons/l10n_br_purchase_request/README.rst
odoo/addons/l10n_br_purchase_request/__init__.py
odoo/addons/l10n_br_purchase_request/__manifest__.py
odoo/addons/l10n_br_purchase_request/i18n/l10n_br_purchase_request.pot
odoo/addons/l10n_br_purchase_request/i18n/pt_BR.po
odoo/addons/l10n_br_purchase_request/readme/CONFIGURE.md
odoo/addons/l10n_br_purchase_request/readme/CONTRIBUTORS.md
odoo/addons/l10n_br_purchase_request/readme/CREDITS.md
odoo/addons/l10n_br_purchase_request/readme/DESCRIPTION.md
odoo/addons/l10n_br_purchase_request/readme/INSTALL.md
odoo/addons/l10n_br_purchase_request/readme/USAGE.md
odoo/addons/l10n_br_purchase_request/static/description/icon.png
odoo/addons/l10n_br_purchase_request/static/description/index.html
odoo/addons/l10n_br_purchase_request/tests/__init__.py
odoo/addons/l10n_br_purchase_request/tests/test_l10n_br_purchase_request.py
odoo/addons/l10n_br_purchase_request/wizards/__init__.py
odoo/addons/l10n_br_purchase_request/wizards/purchase_request_line_make_purchase_order.py
odoo_addon_l10n_br_purchase_request-16.0.2.0.0.dist-info/METADATA
odoo_addon_l10n_br_purchase_request-16.0.2.0.0.dist-info/WHEEL
odoo_addon_l10n_br_purchase_request-16.0.2.0.0.dist-info/top_level.txt
odoo_addon_l10n_br_purchase_request-16.0.2.0.0.dist-info/RECORD
